llm_blender/__init__.py
llm_blender/blender/__init__.py
llm_blender/blender/blender.py
llm_blender/blender/blender_utils.py
llm_blender/blender/config.py
llm_blender/candidates_generation/__init__.py
llm_blender/candidates_generation/engine.py
llm_blender/candidates_generation/eval_candidates.py
llm_blender/candidates_generation/generate_candidates.py
llm_blender/candidates_generation/model_utils.py
llm_blender/common/__init__.py
llm_blender/common/bart_score.py
llm_blender/common/evaluation.py
llm_blender/common/utils.py
llm_blender/download_dataset/__init__.py
llm_blender/download_dataset/get_mixinstruct.py
llm_blender/download_dataset/utils.py
llm_blender/gen_fuser/__init__.py
llm_blender/gen_fuser/config.py
llm_blender/gen_fuser/ds_train.py
llm_blender/gen_fuser/fuse_infer.py
llm_blender/gen_fuser/model_utils.py
llm_blender/gen_fuser/take_subset.py
llm_blender/gen_fuser/test.py
llm_blender/gpt_eval/__init__.py
llm_blender/gpt_eval/cor_eval.py
llm_blender/gpt_eval/gpt_eval.py
llm_blender/gpt_eval/openai_utils.py
llm_blender/gpt_eval/utils.py
llm_blender/pair_ranker/__init__.py
llm_blender/pair_ranker/collator.py
llm_blender/pair_ranker/config.py
llm_blender/pair_ranker/data.py
llm_blender/pair_ranker/layers.py
llm_blender/pair_ranker/loss.py
llm_blender/pair_ranker/model_moe.py
llm_blender/pair_ranker/model_util.py
llm_blender/pair_ranker/pairrm.py
llm_blender/pair_ranker/ranker.py
llm_blender/pair_ranker/trainer.py
llm_blender/pair_ranker/other_rms/__init__.py
llm_blender/pair_ranker/other_rms/starling_rm.py
llm_blender/pair_ranker/other_rms/ultra_rm.py
llm_blender-0.0.2.dist-info/LICENSE
llm_blender-0.0.2.dist-info/METADATA
llm_blender-0.0.2.dist-info/WHEEL
llm_blender-0.0.2.dist-info/top_level.txt
llm_blender-0.0.2.dist-info/RECORD
